LICENSE
iwx_manifest_builder/__init__.py
iwx_manifest_builder/schema/bbox_coord_schema.py
iwx_manifest_builder/schema/bbox_pixels_coord_schema.py
iwx_manifest_builder/schema/category_schema.py
iwx_manifest_builder/schema/chip_detection_schema.py
iwx_manifest_builder/schema/document/detection_schema.py
iwx_manifest_builder/schema/image_schema.py
iwx_manifest_builder/schema/inferred_schema.py
iwx_manifest_builder/schema/keypoints_pixels_coord_schema.py
iwx_manifest_builder/schema/maxar_feature_schema.py
iwx_manifest_builder/schema/point_coord_schema.py
iwx_manifest_builder/schema/polygon_coord_schema.py
iwx_manifest_builder/schema/workflow_schema.py
iwx_manifest_builder-0.0.261.dist-info/LICENSE
iwx_manifest_builder-0.0.261.dist-info/METADATA
iwx_manifest_builder-0.0.261.dist-info/WHEEL
iwx_manifest_builder-0.0.261.dist-info/RECORD
