Metadata-Version: 2.1
Name: iwx-manifest-builder
Version: 0.0.261
Summary: Validates data used in building an iwx manifest file.
Home-page: https://github.com/fsai-dev/fsai-cli-tools
License: MIT
Author: Michael Mohamed
Author-email: michael@foundationstack.com
Requires-Python: >=3.8,<3.12
Classifier: License :: OSI Approved :: MIT License
Classifier: Programming Language :: Python :: 3
Classifier: Programming Language :: Python :: 3.8
Classifier: Programming Language :: Python :: 3.9
Classifier: Programming Language :: Python :: 3.10
Classifier: Programming Language :: Python :: 3.11
Requires-Dist: beartype (>=0.16.4,<0.17.0)
Requires-Dist: loguru (>=0.6.0,<0.7.0)
Requires-Dist: marshmallow (>=3.15.0,<4.0.0)
Requires-Dist: marshmallow-jsonschema (>=0.13.0,<0.14.0)
Project-URL: Repository, https://github.com/fsai-dev/fsai-cli-tools
